{
  "Type": "Standard",
  "Id": "Fk1_6C-7B_1",
  "Line": {
    "Id": "Standard",
    "Text": "He leans in, as if to descend into a conspiratorial whisper, but he never follows through with it."
  },
  "Name": {
    "Id": "Standard",
    "Text": "Narrator"
  },
  "UiPage": "Classic_Dialogue.ui",
  "UiFragment": "Classic_Dialogue_Fragment.ui",
  "Sprite": "sprites/Kweebec_French_Happy.png",
  "Choices": [
    {
      "Id": "Standard",
      "Text": "Continue",
      "Action": {
        "Id": "Advance",
        "Next": "Fk1_6C-7B_2"
      }
    }
  ]
}
